app.py
task_tracker_cli_bryandev-0.1.4.2.dist-info/METADATA
task_tracker_cli_bryandev-0.1.4.2.dist-info/WHEEL
task_tracker_cli_bryandev-0.1.4.2.dist-info/entry_points.txt
task_tracker_cli_bryandev-0.1.4.2.dist-info/top_level.txt
task_tracker_cli_bryandev-0.1.4.2.dist-info/RECORD
