Metadata-Version: 2.4
Name: task_tracker_cli_bryandev
Version: 0.1.4.2
Summary: Simple project for the creation and management of tasks by CLI
Author-email: BryanDev <bryanellis.dev@gmail.com>
Project-URL: Homepage, https://github.com/BryanDevPy/task-tracker-cli
Classifier: Programming Language :: Python :: 3
Classifier: Operating System :: OS Independent
Requires-Python: >=3.9
